django_fstore-0.0.4.dist-info/DESCRIPTION.rst
django_fstore-0.0.4.dist-info/METADATA
django_fstore-0.0.4.dist-info/RECORD
django_fstore-0.0.4.dist-info/WHEEL
django_fstore-0.0.4.dist-info/metadata.json
django_fstore-0.0.4.dist-info/top_level.txt
django_store/__init__.py
django_store/store.py
django_store/urls.py
django_store/views.py
